fitsbits/DejaVuSans.ttf
fitsbits/__init__.py
fitsbits/_coordutils.py
fitsbits/_extractors.py
fitsbits/_modtemplate.py
fitsbits/_modtools.py
fitsbits/_processes.py
fitsbits/_version.py
fitsbits/compression.py
fitsbits/export.py
fitsbits/files.py
fitsbits/fits2export.py
fitsbits/fits2mp4.py
fitsbits/fitshdr.py
fitsbits/operations.py
fitsbits/quality.py
fitsbits-0.1.4.dist-info/LICENSE
fitsbits-0.1.4.dist-info/METADATA
fitsbits-0.1.4.dist-info/WHEEL
fitsbits-0.1.4.dist-info/entry_points.txt
fitsbits-0.1.4.dist-info/top_level.txt
fitsbits-0.1.4.dist-info/RECORD
