Metadata-Version: 2.1
Name: fitsbits
Version: 0.1.4
Summary: Utilities for FITS files: safe (de)compression, exporting to images/movies, parallelized ops on collections, and QA
Home-page: https://github.com/waqasbhatti/fitsbits
Author: Waqas Bhatti
Author-email: waqas.afzal.bhatti@gmail.com
License: MIT
Keywords: astronomy,FITS
Platform: UNKNOWN
Classifier: Development Status :: 4 - Beta
Classifier: License :: OSI Approved :: MIT License
Classifier: Intended Audience :: Science/Research
Classifier: Topic :: Scientific/Engineering :: Astronomy
Classifier: Operating System :: POSIX :: Linux
Classifier: Operating System :: MacOS :: MacOS X
Classifier: Programming Language :: Python :: 3.6
Classifier: Programming Language :: Python :: 3.7
Requires-Python: >=3.6
Requires-Dist: numpy (>=1.14)
Requires-Dist: scipy (>=0.17.0)
Requires-Dist: astropy (>=2.0)
Requires-Dist: Pillow (>=5.2.0)
Requires-Dist: filelock (>=3.0.10)
Requires-Dist: tenacity (>=5.0.4)
Requires-Dist: scikit-learn (>=0.20)
